explainable/__init__.py
explainable/core.py
explainable/entities.py
explainable/py.typed
explainable/replay.py
explainable-1.2.3.dist-info/METADATA
explainable-1.2.3.dist-info/WHEEL
explainable-1.2.3.dist-info/licenses/LICENSE
explainable-1.2.3.dist-info/RECORD
