Metadata-Version: 2.4
Name: explainable
Version: 1.2.3
Summary: Visualise complex data structures in real time
Project-URL: Homepage, https://github.com/numan-ai/explainable
Project-URL: Documentation, https://example.com
Project-URL: Repository, https://github.com/numan-ai/explainable.git
Project-URL: Issues, https://github.com/numan-ai/explainable/issues
Project-URL: Changelog, https://github.com/numan-ai/explainable/blob/master/CHANGELOG.md
Author-email: Numan Team <kostya@numan.ai>
License-Expression: MIT
License-File: LICENSE
Classifier: Development Status :: 4 - Beta
Classifier: Programming Language :: Python
Classifier: Programming Language :: Python :: 3.7
Classifier: Programming Language :: Python :: 3.8
Classifier: Programming Language :: Python :: 3.9
Classifier: Programming Language :: Python :: 3.10
Classifier: Programming Language :: Python :: 3.11
Classifier: Programming Language :: Python :: 3.12
Classifier: Programming Language :: Python :: Implementation :: CPython
Classifier: Programming Language :: Python :: Implementation :: PyPy
Requires-Python: >=3.7
Requires-Dist: typing-extensions>=4.15.0
Requires-Dist: websockets>=14.2
